{
  "name": "Effie Elliott",
  "id": "8466f249-3b57-55e3-bfef-404301c03cab",
  "parents": [
    {
      "name": "Jay Daniels",
      "id": "c20d496c-5b07-551d-9db4-35e17111e4fa",
      "parents": [
        {
          "name": "Johnny Simon",
          "id": "fefb4a75-7736-5be4-ae97-712ea7f97e9f",
          "parents": [
            {
              "name": "Willie Evans",
              "id": "618a8b50-1b83-5db7-b065-0e1d3ed3f76b",
              "parents": [
                {
                  "name": "Pauline Andrews",
                  "id": "539b9134-4dbe-5cb0-aa84-522e4f984341",
                  "parents": [
                    {
                      "name": "Lola Reyes",
                      "id": "258fe4cd-0c70-5b53-a409-bedbe08da157",
                      "parents": [
                        {
                          "name": "Ruth Hudson",
                          "id": "d49bbca0-6197-5347-8b65-b2a7b448cb14",
                          "parents": [
                            {
                              "name": "Eleanor James",
                              "id": "8d4bc98b-2596-53df-804d-f975a9ef4ca8"
                            },
                            {
                              "name": "John Alexander",
                              "id": "3eb50243-b25d-5a91-93c6-ec13611a63bf"
                            }
                          ]
                        },
                        {
                          "name": "Harriett Ramos",
                          "id": "960192b6-53c6-5c66-b05d-038c4e029fd3",
                          "parents": [
                            {
                              "name": "Jordan Glover",
                              "id": "cda26906-3d5a-595f-afad-f8e63f05ed19"
                            },
                            {
                              "name": "Dora French",
                              "id": "81b3c9df-0d5f-5444-9464-70ac1ef72248"
                            }
                          ]
                        }
                      ]
                    },
                    {
                      "name": "Cody Day",
                      "id": "cf80d94f-05f4-5972-85d4-952770c88e58",
                      "parents": [
                        {
                          "name": "Bess Ramirez",
                          "id": "24584995-2b65-5779-87ae-358caf03cd7c",
                          "parents": [
                            {
                              "name": "Ellen Moran",
                              "id": "8eb1fb40-b375-57ca-a54c-db8ccc759806"
                            },
                            {
                              "name": "Willie Kelley",
                              "id": "70d08c49-beb0-5921-8e54-afa09ce6fc2c"
                            }
                          ]
                        },
                        {
                          "name": "Margaret Howard",
                          "id": "6aa93848-f8f7-5a74-8057-e88e4d8e6f04",
                          "parents": [
                            {
                              "name": "Eva Ball",
                              "id": "45004c21-b3e9-52c1-9bc1-e077249f8dbc"
                            },
                            {
                              "name": "Devin Hansen",
                              "id": "421d1bbf-3ddb-52fd-9fab-2d3f8bcb7b77"
                            }
                          ]
                        }
                      ]
                    }
                  ]
                },
                {
                  "name": "Anne Walters",
                  "id": "374a6ca3-d10a-5865-bafb-11388f194a3e",
                  "parents": [
                    {
                      "name": "Maria Poole",
                      "id": "5755154d-25ae-5fef-9938-862f4e252273",
                      "parents": [
                        {
                          "name": "Francisco Powers",
                          "id": "d6d27bd4-1752-56fa-83f3-61cb91ad77fe",
                          "parents": [
                            {
                              "name": "Ralph Mann",
                              "id": "eb009afb-6896-5b95-a165-a2e8291bef80"
                            },
                            {
                              "name": "Lewis Casey",
                              "id": "bf6ae98d-2b1d-545e-8765-8c15c114e49b"
                            }
                          ]
                        },
                        {
                          "name": "Jimmy Abbott",
                          "id": "bac6d54b-953f-57d0-b7e6-4d755f907cdf",
                          "parents": [
                            {
                              "name": "Harriett Rogers",
                              "id": "4c08fc53-4e8f-50b9-89ed-7cfa643e4981"
                            },
                            {
                              "name": "Lelia Jimenez",
                              "id": "12615c1e-0e1c-514e-83ca-e8bb5fc94552"
                            }
                          ]
                        }
                      ]
                    },
                    {
                      "name": "Viola Butler",
                      "id": "36e6f154-6532-51d2-816c-6bde8d2dca46",
                      "parents": [
                        {
                          "name": "Pearl Scott",
                          "id": "e4ab4537-8f22-5068-a440-014a370e2c89",
                          "parents": [
                            {
                              "name": "Elnora Fitzgerald",
                              "id": "c152db60-7392-52e8-acb8-21b647c5f874"
                            },
                            {
                              "name": "Bruce Joseph",
                              "id": "9ae4f391-07d9-56c0-9d9a-5533463a2583"
                            }
                          ]
                        },
                        {
                          "name": "Alex Weber",
                          "id": "c47fae00-297f-59bf-8e69-ea7185c9ece0",
                          "parents": [
                            {
                              "name": "Russell McLaughlin",
                              "id": "3bda6476-d6a8-5b0d-8ce0-2aefc4869545"
                            },
                            {
                              "name": "Stephen Love",
                              "id": "3ada2052-7980-5b26-bea3-a23bf7798a74"
                            }
                          ]
                        }
                      ]
                    }
                  ]
                }
              ]
            },
            {
              "name": "Florence Davis",
              "id": "a4ffc2f0-693e-5acc-bebd-82863af2aa38",
              "parents": [
                {
                  "name": "Eva Armstrong",
                  "id": "f374d0dd-1ba3-5832-b748-c24e12f48429",
                  "parents": [
                    {
                      "name": "Matthew Cohen",
                      "id": "e4f8a638-6ca2-5fa2-afb4-38215dbf593e",
                      "parents": [
                        {
                          "name": "Manuel McGuire",
                          "id": "526ec95a-61c5-5a1e-bcc0-4b0f90a4672f",
                          "parents": [
                            {
                              "name": "George Tate",
                              "id": "0ca04809-8050-5030-8370-085e7e4fa6e0"
                            },
                            {
                              "name": "Estella Wright",
                              "id": "ccd77ae8-7bfa-5f2f-aada-e771339dd770"
                            }
                          ]
                        },
                        {
                          "name": "Devin Singleton",
                          "id": "13b43b04-b9f6-57e6-b889-2f69bfb0d128",
                          "parents": [
                            {
                              "name": "Clifford Manning",
                              "id": "6265589e-17bf-5f00-b429-bcb40f750939"
                            },
                            {
                              "name": "Maggie Pratt",
                              "id": "f75ea069-1556-5f58-8628-065ed4540a10"
                            }
                          ]
                        }
                      ]
                    },
                    {
                      "name": "Jessie Mendez",
                      "id": "1be79efc-cdeb-5317-848e-2e8a4010e117",
                      "parents": [
                        {
                          "name": "Lenora Schmidt",
                          "id": "6deb4186-2d6c-556a-94f2-d29e0bcea15b",
                          "parents": [
                            {
                              "name": "Eddie Santiago",
                              "id": "fe829f45-f829-5067-b362-b40f36892791"
                            },
                            {
                              "name": "Leah Brooks",
                              "id": "cd276b5a-a9f8-568e-a8b8-382934df5e3b"
                            }
                          ]
                        },
                        {
                          "name": "Corey Norman",
                          "id": "163e8292-8fe9-5454-abef-319b3729d7ff",
                          "parents": [
                            {
                              "name": "Blake Hawkins",
                              "id": "50ced8bf-8dc4-5420-a8b5-8fd87966cbab"
                            },
                            {
                              "name": "Allen Waters",
                              "id": "38a1756a-d17c-5394-beb2-37760c82e36d"
                            }
                          ]
                        }
                      ]
                    }
                  ]
                },
                {
                  "name": "Fanny Nash",
                  "id": "15560b1d-2caa-54e7-8b76-54f4cc9fa170",
                  "parents": [
                    {
                      "name": "Harriet Floyd",
                      "id": "31e13714-2ec3-551e-97b8-02d2eaab0d83",
                      "parents": [
                        {
                          "name": "Leona Chapman",
                          "id": "121fc00d-effd-54a2-8491-b26cce4d5edb",
                          "parents": [
                            {
                              "name": "Louise Alexander",
                              "id": "250279d2-3515-53fa-b5eb-6db198af8ec2"
                            },
                            {
                              "name": "Anne Dennis",
                              "id": "f3d20682-b7b9-5b5e-b87b-ed225681b29f"
                            }
                          ]
                        },
                        {
                          "name": "Cora Ortiz",
                          "id": "995ff30e-fc94-5c1a-99c2-2e1c8d897ff7",
                          "parents": [
                            {
                              "name": "Danny Sherman",
                              "id": "a190330a-dcdf-5c4a-80de-757396ff9908"
                            },
                            {
                              "name": "Jeff Riley",
                              "id": "b2a8d9b9-7d6c-549d-b00a-b7ce9e1ddd76"
                            }
                          ]
                        }
                      ]
                    },
                    {
                      "name": "Luke Tucker",
                      "id": "6767557e-d20b-5a03-a1aa-a9b969c09b14",
                      "parents": [
                        {
                          "name": "Susie Tate",
                          "id": "122e04d2-57f1-5d8d-b775-3f7973b1797e",
                          "parents": [
                            {
                              "name": "Dean James",
                              "id": "40dc83a5-302b-56cc-a792-c9f8b3eeeb48"
                            },
                            {
                              "name": "Timothy Santos",
                              "id": "0cde891c-ca58-50ae-8294-29f3ad273311"
                            }
                          ]
                        },
                        {
                          "name": "Janie Morrison",
                          "id": "91305d55-e236-5325-aeb1-d80200357f7f",
                          "parents": [
                            {
                              "name": "Curtis Olson",
                              "id": "e1ec65e4-f9b8-5df0-9fd7-f6167e212a1d"
                            },
                            {
                              "name": "Catherine James",
                              "id": "05241278-fc0c-548a-97a6-86a43a3a8d31"
                            }
                          ]
                        }
                      ]
                    }
                  ]
                }
              ]
            }
          ]
        },
        {
          "name": "Elizabeth Shaw",
          "id": "b59af683-5d85-523d-a600-739ae33447f8",
          "parents": [
            {
              "name": "Kate Ruiz",
              "id": "682aebd6-a2f1-5fd3-8d3a-8a7de7b38e8f",
              "parents": [
                {
                  "name": "Leah Scott",
                  "id": "50bb96b9-0093-529b-87d9-b6ea91c45ab6",
                  "parents": [
                    {
                      "name": "Aiden Mendez",
                      "id": "7c5ccf66-ee91-5f14-ba14-a1a59405d62f",
                      "parents": [
                        {
                          "name": "Jeffery Stewart",
                          "id": "8469a050-f1c5-59f9-becd-24e1e901b081",
                          "parents": [
                            {
                              "name": "Emma Rowe",
                              "id": "79621803-363c-5a0a-9228-71b0b2fb5f92"
                            },
                            {
                              "name": "Lora Page",
                              "id": "4d377c09-6f2e-57f6-9d6a-ae25e278056a"
                            }
                          ]
                        },
                        {
                          "name": "Sarah Townsend",
                          "id": "01286a7c-da60-5a03-89c5-39ffd0e4fa27",
                          "parents": [
                            {
                              "name": "Ina Underwood",
                              "id": "a5e0c248-d07d-564e-a6f6-5a38b3b68fd6"
                            },
                            {
                              "name": "Loretta McGee",
                              "id": "224f4f62-a134-5455-9ddb-97bf83c3ab59"
                            }
                          ]
                        }
                      ]
                    },
                    {
                      "name": "Belle Brady",
                      "id": "f209d423-ed8a-5dcc-ae9e-ca2c7dc3c0bc",
                      "parents": [
                        {
                          "name": "Lilly Hoffman",
                          "id": "aa565648-2fb6-58d5-bd2b-e7b56b446497",
                          "parents": [
                            {
                              "name": "Charlotte Reed",
                              "id": "7d2e84ef-4c62-5970-8a1c-6b91335770ec"
                            },
                            {
                              "name": "Derrick White",
                              "id": "043df3c0-e727-5d93-9c48-97db48d40163"
                            }
                          ]
                        },
                        {
                          "name": "Jeffery Chavez",
                          "id": "eb44ba89-7c52-5b06-8a09-64ad4c856444",
                          "parents": [
                            {
                              "name": "Warren Porter",
                              "id": "9831c2bc-9296-5c9c-955a-4966f48277c0"
                            },
                            {
                              "name": "Cody Garrett",
                              "id": "76cd6bb8-535c-5d9f-9c56-952adaab4c19"
                            }
                          ]
                        }
                      ]
                    }
                  ]
                },
                {
                  "name": "Ora Scott",
                  "id": "91e9543f-828d-5fc2-b235-b55f0d9ee946",
                  "parents": [
                    {
                      "name": "Brent Lyons",
                      "id": "7baede44-4cb5-55cb-b962-5c5b563dccfc",
                      "parents": [
                        {
                          "name": "Eugene Vaughn",
                          "id": "2a263bcf-a545-5c62-ba2c-a43c66f351c0",
                          "parents": [
                            {
                              "name": "Roxie Terry",
                              "id": "da9d4cb2-f800-5bb4-abee-f9a4c62bf039"
                            },
                            {
                              "name": "Alice Reyes",
                              "id": "51ac878c-de8f-5903-b95f-456922cf26f2"
                            }
                          ]
                        },
                        {
                          "name": "Leo Francis",
                          "id": "9449feed-260c-5eeb-8706-cde947a41e04",
                          "parents": [
                            {
                              "name": "Tom Murray",
                              "id": "0fc7a0b1-4a7e-54d3-9e55-a0f43bcb32a3"
                            },
                            {
                              "name": "Cody Wise",
                              "id": "50fa0ae9-6a32-5055-8cfa-53189a2d0c50"
                            }
                          ]
                        }
                      ]
                    },
                    {
                      "name": "Rosetta Bailey",
                      "id": "5626c5c1-7739-5122-9a6b-761de44151a1",
                      "parents": [
                        {
                          "name": "Mae Waters",
                          "id": "0a5dded0-07f0-5ce2-8e99-95df3a2186e3",
                          "parents": [
                            {
                              "name": "Claudia Craig",
                              "id": "72b234d6-39d5-51dc-8225-def10dca7b00"
                            },
                            {
                              "name": "Corey Bowen",
                              "id": "dabdcea7-d56e-5878-8b99-19034a53433e"
                            }
                          ]
                        },
                        {
                          "name": "Clayton Holland",
                          "id": "df1ceb5e-017b-5da3-962a-c02388da3864",
                          "parents": [
                            {
                              "name": "Genevieve Butler",
                              "id": "4a8333cc-24f2-5eb2-beaf-2b2b3c8bbaf7"
                            },
                            {
                              "name": "Lou Lopez",
                              "id": "18e1482c-7d42-5916-a5a3-521f58688402"
                            }
                          ]
                        }
                      ]
                    }
                  ]
                }
              ]
            },
            {
              "name": "Ann Brooks",
              "id": "a2c8822a-eb78-59f1-9177-d9ec851e8f1b",
              "parents": [
                {
                  "name": "Vera Rice",
                  "id": "f0ce6b18-86c4-5de6-9b93-d47eff93f021",
                  "parents": [
                    {
                      "name": "Marvin Jefferson",
                      "id": "3c698ac4-ead2-5111-88fb-f2bb659e4901",
                      "parents": [
                        {
                          "name": "Abbie Baker",
                          "id": "a28a7f4f-a618-577b-9443-a28fb629957b",
                          "parents": [
                            {
                              "name": "Juan Lee",
                              "id": "cec06edc-b4a2-5d48-b2bd-289212139066"
                            },
                            {
                              "name": "Lulu Huff",
                              "id": "949f4e1d-3db3-5837-b627-f7d40822db94"
                            }
                          ]
                        },
                        {
                          "name": "Eddie Morrison",
                          "id": "4ac0b9fa-31ec-5321-90b2-69e363403e13",
                          "parents": [
                            {
                              "name": "Leah Lynch",
                              "id": "b638f34f-80c9-54ee-a74f-ee97f5d7e574"
                            },
                            {
                              "name": "Samuel Lane",
                              "id": "f6542891-7c69-500a-9dcd-758db7173fc1"
                            }
                          ]
                        }
                      ]
                    },
                    {
                      "name": "Mina Lopez",
                      "id": "7c210cc2-37bf-5399-a691-482885b13d63",
                      "parents": [
                        {
                          "name": "Danny Willis",
                          "id": "95d897cc-2d04-551e-b3fe-f43c2130c276",
                          "parents": [
                            {
                              "name": "Nora Summers",
                              "id": "6a3c1a89-1341-58f6-8981-94be387b4b8a"
                            },
                            {
                              "name": "Lola Hicks",
                              "id": "a76538c6-9c38-5fbf-81d0-d7520dc276a8"
                            }
                          ]
                        },
                        {
                          "name": "Chester Bell",
                          "id": "e3065f16-20cf-5be9-8d48-0561c9681e56",
                          "parents": [
                            {
                              "name": "Janie White",
                              "id": "4414be55-13e3-53bc-a16c-dab46b3a59fd"
                            },
                            {
                              "name": "Brett Stephens",
                              "id": "a926cf64-16c0-5310-9a82-a62572020daa"
                            }
                          ]
                        }
                      ]
                    }
                  ]
                },
                {
                  "name": "James Patton",
                  "id": "f8829767-32f9-5aa5-89b3-b0eb3467a447",
                  "parents": [
                    {
                      "name": "Paul Jordan",
                      "id": "9f92637f-20c2-5568-81a5-555e8a2cabae",
                      "parents": [
                        {
                          "name": "Clarence Walters",
                          "id": "b32c13f2-6aaf-50d1-92a7-39d972a1c5b3",
                          "parents": [
                            {
                              "name": "Lela Cain",
                              "id": "5e9e7055-7c85-53fd-be80-cd039df137b7"
                            },
                            {
                              "name": "Jack Long",
                              "id": "c21b058a-3b06-5a2a-9ffe-3bf1f93c8485"
                            }
                          ]
                        },
                        {
                          "name": "Wayne Parsons",
                          "id": "c9b8a3c8-480a-590b-aa36-04a72196a41d",
                          "parents": [
                            {
                              "name": "Steve Roy",
                              "id": "34093c05-da20-5808-9fb2-4eb452b1a36c"
                            },
                            {
                              "name": "Catherine Bryant",
                              "id": "d900fa87-efb0-58a9-8079-13e40f193f2f"
                            }
                          ]
                        }
                      ]
                    },
                    {
                      "name": "Beulah Shaw",
                      "id": "56014780-6ff4-5d53-90da-5d079316d932",
                      "parents": [
                        {
                          "name": "Alexander Davis",
                          "id": "923dfe03-f895-572b-8407-5f7a7eee9286",
                          "parents": [
                            {
                              "name": "Isaac Vaughn",
                              "id": "6b6c08d4-588a-5902-b7c5-0517bd707280"
                            },
                            {
                              "name": "Margaret Murray",
                              "id": "68fe06fa-71fa-5738-92be-0d8dc7c70210"
                            }
                          ]
                        },
                        {
                          "name": "Tillie Hardy",
                          "id": "8d8f4ed5-b366-52df-a36d-3c3089029f42",
                          "parents": [
                            {
                              "name": "Mildred Sparks",
                              "id": "eec1abf7-61a2-5012-8f0a-6047084ca8aa"
                            },
                            {
                              "name": "Lora Dunn",
                              "id": "43f7a7d1-d181-5a25-aff8-cb0dbac905ab"
                            }
                          ]
                        }
                      ]
                    }
                  ]
                }
              ]
            }
          ]
        }
      ]
    },
    {
      "name": "Eugene Jones",
      "id": "85bd2c55-f9f3-5cc0-99b5-c781739a0bd6",
      "parents": [
        {
          "name": "Ollie Alexander",
          "id": "4b158cb2-1150-5d93-a8c2-8d6c3f78bd30",
          "parents": [
            {
              "name": "Curtis Cross",
              "id": "913ef548-fc21-523c-81b8-a763432ddce1",
              "parents": [
                {
                  "name": "Jeffery Manning",
                  "id": "4d5f25df-cedf-53cb-80f1-39ee1338d5a1",
                  "parents": [
                    {
                      "name": "Mae Steele",
                      "id": "7cf14d59-5dd8-55b7-8a78-1ef48ea1ca03",
                      "parents": [
                        {
                          "name": "Anthony Stanley",
                          "id": "96697794-5c43-5684-a5be-783825884a72",
                          "parents": [
                            {
                              "name": "Rosetta Bryant",
                              "id": "c4cc2aa0-50f8-5e96-bece-89ad84047cfd"
                            },
                            {
                              "name": "Carrie Simmons",
                              "id": "4ff2f104-54d7-5375-925b-99cf46127781"
                            }
                          ]
                        },
                        {
                          "name": "Estelle Williamson",
                          "id": "b4710b14-a06c-53a5-a385-0950d91e0146",
                          "parents": [
                            {
                              "name": "Raymond Hayes",
                              "id": "68aa4d84-1be1-522c-bf98-d8386fe4342d"
                            },
                            {
                              "name": "Lucille Pittman",
                              "id": "96253013-05df-5fca-a915-571e8a4537c9"
                            }
                          ]
                        }
                      ]
                    },
                    {
                      "name": "Hannah Moreno",
                      "id": "937599ef-7830-521b-870e-2e36f21bd140",
                      "parents": [
                        {
                          "name": "Erik Wong",
                          "id": "7b56de5f-f892-5e89-9a8b-1de9ce4572de",
                          "parents": [
                            {
                              "name": "Corey Weaver",
                              "id": "c5b41cd3-3493-5179-a24a-48bfd380334d"
                            },
                            {
                              "name": "Charlotte Burns",
                              "id": "0f06c849-25e7-542d-a720-df144bfa4759"
                            }
                          ]
                        },
                        {
                          "name": "Caroline Miles",
                          "id": "20b79bf8-eda4-5db0-9dd6-d04ebd2bf2a4",
                          "parents": [
                            {
                              "name": "Edgar Gordon",
                              "id": "cf7c9b82-1e92-5749-8b3c-647c364b58e6"
                            },
                            {
                              "name": "Inez Peterson",
                              "id": "39c69098-57d4-5ac4-abcf-9b69005b8723"
                            }
                          ]
                        }
                      ]
                    }
                  ]
                },
                {
                  "name": "Kyle Rhodes",
                  "id": "70df0187-2842-5cb9-97fb-78d7f1a97060",
                  "parents": [
                    {
                      "name": "Nicholas Murray",
                      "id": "063b7da5-7806-54a4-847a-c40f538180f8",
                      "parents": [
                        {
                          "name": "Alex Brady",
                          "id": "6f55ffb8-839d-5253-80a5-f41fed067e60",
                          "parents": [
                            {
                              "name": "Ronnie Boyd",
                              "id": "7bab57c2-eb7d-5de2-b572-d2c93c67d9e9"
                            },
                            {
                              "name": "Leo Gibbs",
                              "id": "7754249f-8ac1-5684-883b-ba99c475235b"
                            }
                          ]
                        },
                        {
                          "name": "Lucy Gregory",
                          "id": "88218d8b-4395-5d0b-bd33-692b4a47d5ac",
                          "parents": [
                            {
                              "name": "Andre Silva",
                              "id": "d1e1c1ad-75bd-59cd-a2f5-56cc5fd08f65"
                            },
                            {
                              "name": "Arthur Larson",
                              "id": "88c00345-7dc0-5900-acd3-d15057102f2b"
                            }
                          ]
                        }
                      ]
                    },
                    {
                      "name": "Georgia Hardy",
                      "id": "ba48bf57-d563-55cb-a23a-9444430b19c3",
                      "parents": [
                        {
                          "name": "Eugenia Burgess",
                          "id": "15475961-7566-5b32-bb36-b94a12b3e4aa",
                          "parents": [
                            {
                              "name": "Craig Leonard",
                              "id": "aacfa6ef-a556-5e4e-958a-c65f950f8b80"
                            },
                            {
                              "name": "John Daniel",
                              "id": "9fa4b8f2-e48d-5efb-9901-59cbfc5ab700"
                            }
                          ]
                        },
                        {
                          "name": "Sue Ingram",
                          "id": "e8050742-6d58-54ca-afc9-7293062acc09",
                          "parents": [
                            {
                              "name": "Ruby Floyd",
                              "id": "5a9eb7ad-e96b-5520-8317-2c6922be326d"
                            },
                            {
                              "name": "Jessie Zimmerman",
                              "id": "bf5e542f-10bc-5221-a613-09156e2bfbb4"
                            }
                          ]
                        }
                      ]
                    }
                  ]
                }
              ]
            },
            {
              "name": "Madge West",
              "id": "a79e51ad-d86e-5376-abce-5bd45e3d60d1",
              "parents": [
                {
                  "name": "Mathilda Pearson",
                  "id": "c2c44582-1005-5bf6-8eb5-e4e1fd1fa44b",
                  "parents": [
                    {
                      "name": "Mildred Hunt",
                      "id": "2e80a1d5-7367-5f0d-b111-2477b1c80fba",
                      "parents": [
                        {
                          "name": "Kenneth Curtis",
                          "id": "ae637fc3-6219-58f6-919c-6d4a6e209a90",
                          "parents": [
                            {
                              "name": "Teresa Poole",
                              "id": "b8a09f32-76e6-5a31-8c07-7285b116881b"
                            },
                            {
                              "name": "Eugene Klein",
                              "id": "855d7b1c-a8a3-5e2c-b180-8f6548aeb0ba"
                            }
                          ]
                        },
                        {
                          "name": "Eva Harper",
                          "id": "bb8dd802-cf63-5b9c-bda6-3ca14281c6d8",
                          "parents": [
                            {
                              "name": "Lula Beck",
                              "id": "1d9b5d9b-2f8e-5824-ac1c-161a94696969"
                            },
                            {
                              "name": "Victoria Wise",
                              "id": "2497cf93-3fc6-578c-9198-9efd3b68f2ae"
                            }
                          ]
                        }
                      ]
                    },
                    {
                      "name": "Max Todd",
                      "id": "9d9044ff-8641-5bd4-a4f2-fecfa139f042",
                      "parents": [
                        {
                          "name": "Ernest Kennedy",
                          "id": "854c6460-747f-5d8c-a69a-dff95de92aff",
                          "parents": [
                            {
                              "name": "Helena Ballard",
                              "id": "51d9c5f7-9478-5945-8d33-bbc4ce3a1d58"
                            },
                            {
                              "name": "Glenn Richardson",
                              "id": "25d8b17c-4fb1-5992-ba96-3a103ffb90f6"
                            }
                          ]
                        },
                        {
                          "name": "Amelia Moran",
                          "id": "9c8ac2fc-c985-50f8-83cf-652077cd5ef2",
                          "parents": [
                            {
                              "name": "Bettie Webster",
                              "id": "839abae0-864a-5188-bc86-d5f1f0dcc88b"
                            },
                            {
                              "name": "Charlotte Vega",
                              "id": "851976e6-30a7-5517-bb60-6a179399a021"
                            }
                          ]
                        }
                      ]
                    }
                  ]
                },
                {
                  "name": "Hulda Chavez",
                  "id": "151ff88c-c7d2-57b1-aee6-c1b1556305c1",
                  "parents": [
                    {
                      "name": "Ralph Lamb",
                      "id": "320b8a0b-b298-51ea-b0d2-ed093dbf452a",
                      "parents": [
                        {
                          "name": "Chase Hicks",
                          "id": "0890b8d4-b302-5c57-86c1-7f95adfec6fb",
                          "parents": [
                            {
                              "name": "Sophia Elliott",
                              "id": "fbcf875d-5ca4-5706-8765-a3a85989ba53"
                            },
                            {
                              "name": "Owen Kelly",
                              "id": "5b41940e-b8f6-528e-99bf-a1ce1cd64e2d"
                            }
                          ]
                        },
                        {
                          "name": "Pauline Gardner",
                          "id": "1954a02d-70d1-5c8b-80ad-78479be39edf",
                          "parents": [
                            {
                              "name": "Anne Rowe",
                              "id": "c41c04e2-7054-53d2-9b3a-f0604880d222"
                            },
                            {
                              "name": "Georgia Bowman",
                              "id": "31add2c0-e90d-504f-b282-e02f6f5c385e"
                            }
                          ]
                        }
                      ]
                    },
                    {
                      "name": "Francisco Welch",
                      "id": "6d92c880-2bc7-578e-844e-995b8e9e0e44",
                      "parents": [
                        {
                          "name": "Bessie Jenkins",
                          "id": "760db3f3-1f6d-5c43-86f3-e1331fe77f63",
                          "parents": [
                            {
                              "name": "Marc Keller",
                              "id": "19d470d0-8598-593f-8f69-dd59a7d11f0f"
                            },
                            {
                              "name": "Bryan Williams",
                              "id": "c28c5a9c-ae1b-5670-bc16-7982d827f114"
                            }
                          ]
                        },
                        {
                          "name": "Maude Torres",
                          "id": "b8e589a4-4dd1-59ef-88c1-9c8c8026c594",
                          "parents": [
                            {
                              "name": "Hattie Ray",
                              "id": "f1791456-114d-5238-b326-49e752dafd13"
                            },
                            {
                              "name": "Derrick Rodgers",
                              "id": "c1a6fc64-9a66-5e82-bed8-71523fec407c"
                            }
                          ]
                        }
                      ]
                    }
                  ]
                }
              ]
            }
          ]
        },
        {
          "name": "Charlie Wallace",
          "id": "49bd9d99-808e-5307-bc3a-bb3ccec266cf",
          "parents": [
            {
              "name": "Katherine Alvarado",
              "id": "6db6611e-29f3-5dbb-aab8-12b0a412adb8",
              "parents": [
                {
                  "name": "Jackson Fletcher",
                  "id": "978c8d57-e3f5-5c45-85dc-aef3305c7c14",
                  "parents": [
                    {
                      "name": "Jon Schmidt",
                      "id": "5fb664b5-15ed-524c-a498-7ee091bdb6e3",
                      "parents": [
                        {
                          "name": "Delia Fuller",
                          "id": "0984acb1-727b-5b89-96c6-42f96c10557a",
                          "parents": [
                            {
                              "name": "Georgia Lindsey",
                              "id": "0545588c-c7c1-592e-8a7c-64e98fe5d98f"
                            },
                            {
                              "name": "Ophelia Weber",
                              "id": "dac56ba5-1238-50ac-9ded-8731406c94d7"
                            }
                          ]
                        },
                        {
                          "name": "Cody Burke",
                          "id": "cc767f10-8f32-5650-a090-7d648f2bac9d",
                          "parents": [
                            {
                              "name": "Cecelia Gill",
                              "id": "5fe2b707-05d9-51cf-a96a-7137d1aa31e9"
                            },
                            {
                              "name": "Norman Joseph",
                              "id": "8c37118d-1cee-58ac-9bc3-a64ee3dc08b3"
                            }
                          ]
                        }
                      ]
                    },
                    {
                      "name": "Fannie Love",
                      "id": "5d513d0d-895d-5a39-b5a0-f23f51563158",
                      "parents": [
                        {
                          "name": "Fanny Coleman",
                          "id": "f57751dd-ed13-5d36-8516-6e73582301cc",
                          "parents": [
                            {
                              "name": "Mittie Palmer",
                              "id": "9bb7042e-0784-52ae-8084-20e1cb61e307"
                            },
                            {
                              "name": "Delia Mason",
                              "id": "35a779d4-94a7-5d86-a1b8-5d7b677db6c5"
                            }
                          ]
                        },
                        {
                          "name": "Maude Luna",
                          "id": "88def318-bd89-50b2-85be-16d08922de73",
                          "parents": [
                            {
                              "name": "Jordan Bush",
                              "id": "4687549c-bb96-5216-b2e3-fa81b4028193"
                            },
                            {
                              "name": "Hulda Soto",
                              "id": "a30ed509-89c7-50f2-9fe7-9ee459b2a98b"
                            }
                          ]
                        }
                      ]
                    }
                  ]
                },
                {
                  "name": "Tillie Klein",
                  "id": "35eb3c47-856b-5201-8ad0-5580c7abc2f7",
                  "parents": [
                    {
                      "name": "Nora Terry",
                      "id": "9dc55ec5-6964-5ecb-a113-678a78979edc",
                      "parents": [
                        {
                          "name": "Ray Webb",
                          "id": "44c3e042-ddbe-59dc-b9d7-e5f2a6a58eb6",
                          "parents": [
                            {
                              "name": "Cole Evans",
                              "id": "6cedbf5a-2e6f-5606-b26f-0f16e0edce29"
                            },
                            {
                              "name": "May Gomez",
                              "id": "3e87fe21-48e5-5f21-8906-b888a1506af7"
                            }
                          ]
                        },
                        {
                          "name": "Gavin Watts",
                          "id": "ae15f58e-1144-5dac-abb8-36ad95caecd5",
                          "parents": [
                            {
                              "name": "Luke George",
                              "id": "05fc4412-0ac4-5cff-ae6d-b13fcafd292f"
                            },
                            {
                              "name": "Luella Rose",
                              "id": "dbd270f1-ebb2-5a45-88ab-3e31fdd08f40"
                            }
                          ]
                        }
                      ]
                    },
                    {
                      "name": "Ethel Murray",
                      "id": "d2f70579-0d97-5b3c-9368-4d8740d9a73f",
                      "parents": [
                        {
                          "name": "Jorge Daniels",
                          "id": "33074712-e8b1-5bf7-a736-b4e53bd1b0ec",
                          "parents": [
                            {
                              "name": "Rena McKenzie",
                              "id": "e738da16-489b-528a-be5a-1b2e861cc1a9"
                            },
                            {
                              "name": "Hester Brady",
                              "id": "57927783-3723-5bd7-8c7a-dd7ff19fd813"
                            }
                          ]
                        },
                        {
                          "name": "Jean Perkins",
                          "id": "cc8fa600-9da4-529c-936e-84b73ac638af",
                          "parents": [
                            {
                              "name": "Isabel Cooper",
                              "id": "91a55fba-710f-51df-8ee8-1fce16d01626"
                            },
                            {
                              "name": "Dean Brewer",
                              "id": "f196b40b-4d23-5fe6-b677-8f2167e58ea7"
                            }
                          ]
                        }
                      ]
                    }
                  ]
                }
              ]
            },
            {
              "name": "Norman Gomez",
              "id": "84469ab3-d5fb-537c-933a-51b9384ecb61",
              "parents": [
                {
                  "name": "Gilbert Jimenez",
                  "id": "2d1cda43-50af-55b0-b117-e70d9a5855df",
                  "parents": [
                    {
                      "name": "Mathilda Romero",
                      "id": "fdfdcc5d-490f-5a75-8369-7eb65aac97c5",
                      "parents": [
                        {
                          "name": "Eliza Robinson",
                          "id": "25fb2a30-b8b0-5c35-b2a6-e165b8a785f4",
                          "parents": [
                            {
                              "name": "Etta Nunez",
                              "id": "a239cb4c-63b9-5446-af43-882ef7fe3d2d"
                            },
                            {
                              "name": "Mable Strickland",
                              "id": "fb1859a1-f3d8-5952-9a7a-e0b08a5c4b9b"
                            }
                          ]
                        },
                        {
                          "name": "Blake Reese",
                          "id": "6541a1e8-6eec-526e-a873-c264c12b1a0d",
                          "parents": [
                            {
                              "name": "Robert Thornton",
                              "id": "b17b22c4-3c3e-5221-8876-81c024319983"
                            },
                            {
                              "name": "Franklin Barrett",
                              "id": "51f699e2-5a0e-50b9-983d-e49b658306b6"
                            }
                          ]
                        }
                      ]
                    },
                    {
                      "name": "Helena Medina",
                      "id": "2a3a8df2-7458-5573-918a-bdc8fea04e69",
                      "parents": [
                        {
                          "name": "Teresa Barrett",
                          "id": "c45f68ad-31ae-5172-9409-e60e023b1464",
                          "parents": [
                            {
                              "name": "Johanna Crawford",
                              "id": "590095f3-f533-5c4a-83ce-6c8c652800e5"
                            },
                            {
                              "name": "Henry Foster",
                              "id": "ed22bed2-a0f1-5618-b6bf-5cee8e83c3bb"
                            }
                          ]
                        },
                        {
                          "name": "Julia Swanson",
                          "id": "0697166b-ce02-52f4-8131-70c57cb8620a",
                          "parents": [
                            {
                              "name": "James Pearson",
                              "id": "b22bec0f-130a-5cca-a870-4a97442317a9"
                            },
                            {
                              "name": "Hunter Rios",
                              "id": "0062c60e-b99f-520a-8b71-b204c632acea"
                            }
                          ]
                        }
                      ]
                    }
                  ]
                },
                {
                  "name": "Chester Lawrence",
                  "id": "1279a86d-4d02-5e64-aff9-460a1c9ccf3e",
                  "parents": [
                    {
                      "name": "Mable Rowe",
                      "id": "a305104c-07a1-58a3-9bb5-b2f21ac44111",
                      "parents": [
                        {
                          "name": "Nicholas Mullins",
                          "id": "40dfab68-32cb-5add-91c1-8658d461e015",
                          "parents": [
                            {
                              "name": "Susie Little",
                              "id": "55a92e1e-0d93-525c-8365-60557aad4eb4"
                            },
                            {
                              "name": "Kathryn Nelson",
                              "id": "7504e193-b9c6-5c3a-91ba-8eb413f172eb"
                            }
                          ]
                        },
                        {
                          "name": "Lettie Salazar",
                          "id": "e74bf8a8-3988-5648-865e-dc27dc7ca66d",
                          "parents": [
                            {
                              "name": "Noah Romero",
                              "id": "9fee6b87-a6e9-5b76-a398-7c98d33c7284"
                            },
                            {
                              "name": "Lola McGee",
                              "id": "1c87f67a-a521-5d06-8b83-739b081419a7"
                            }
                          ]
                        }
                      ]
                    },
                    {
                      "name": "Lily Poole",
                      "id": "15985a4f-6dea-5543-94aa-6308e2a3a971",
                      "parents": [
                        {
                          "name": "Clayton Summers",
                          "id": "0c2415a2-c482-5cba-b188-2c0c0633ed2b",
                          "parents": [
                            {
                              "name": "Joseph Murphy",
                              "id": "2a2649c9-71b7-5857-bf68-5055089ddd0a"
                            },
                            {
                              "name": "Etta Lindsey",
                              "id": "411d179b-0a74-5a27-bf77-49b35ca4a789"
                            }
                          ]
                        },
                        {
                          "name": "Clifford Malone",
                          "id": "5813ed74-3cfa-5c16-b72c-8d0e0f7f2874",
                          "parents": [
                            {
                              "name": "Stephen Jacobs",
                              "id": "410059b8-95e3-5c0e-86b9-a75d2524e3cc"
                            },
                            {
                              "name": "Sylvia Frank",
                              "id": "bae81a28-7e0a-55aa-91e2-e5c35a0aad29"
                            }
                          ]
                        }
                      ]
                    }
                  ]
                }
              ]
            }
          ]
        }
      ]
    }
  ]
}
